<?xml version="1.0"?>
<pklist version="1.0" creator="flexAnalysis 3.4.76.0" shots="8000" date="2021-05-13T16:37:46.601+02:00" spectrumid="DF13F192-C924-4CE0-8B0C-CADC2393A2A9">
<pk>
<absi>22902.29102261403</absi>
<area>3999.457344782812</area>
<chisq>11220600.37117717</chisq>
<goodn>224.0282262087257</goodn>
<goodn2>0.6250297646510247</goodn2>
<ind>56234.26406789859</ind>
<lind>56206.00000000000</lind>
<lmass>1131.483641899499</lmass>
<mass>1131.726685751538</mass>
<massemg>1131.721152898670</massemg>
<massgaussian>1131.726892722835</massgaussian>
<meth>4</meth>
<reso>11771.93400731025</reso>
<rind>56726.00000000000</rind>
<rmass>1135.959337723844</rmass>
<s2n>6.055859002482380</s2n>
<sigmaemg>0.04045100196572093</sigmaemg>
<tauemg>0.005636624025328274</tauemg>
<type>0</type>
</pk>
<pk>
<absi>12602.00150669084</absi>
<area>2713.100350870498</area>
<chisq>394269.7449108466</chisq>
<goodn>7397.148566090773</goodn>
<goodn2>0.9263110637513589</goodn2>
<ind>124178.1788631124</ind>
<lind>124158.0000000000</lind>
<lmass>1791.518831410031</lmass>
<mass>1791.737333511052</mass>
<massemg>1791.721222720165</massemg>
<massgaussian>1791.739193666000</massgaussian>
<meth>4</meth>
<reso>22626.90039436707</reso>
<rind>124656.0000000000</rind>
<rmass>1796.915211800310</rmass>
<s2n>6.423061215590405</s2n>
<sigmaemg>0.02952829116520661</sigmaemg>
<tauemg>0.02038411320245359</tauemg>
<type>0</type>
</pk>
<pk>
<absi>7772.425543620980</absi>
<area>2251.078111628171</area>
<chisq>110043.5196211321</chisq>
<goodn>36535.85507262067</goodn>
<goodn2>0.9667244894637790</goodn2>
<ind>174960.7739775295</ind>
<lind>174942.0000000000</lind>
<lmass>2383.724993877222</lmass>
<mass>2383.959577816162</mass>
<massemg>2383.935702083065</massemg>
<massgaussian>2383.966626022445</massgaussian>
<meth>4</meth>
<reso>27960.57902014504</reso>
<rind>175456.0000000000</rind>
<rmass>2390.151688149985</rmass>
<s2n>17.18007279449569</s2n>
<sigmaemg>0.02492745690369702</sigmaemg>
<tauemg>0.04396617936390612</tauemg>
<type>0</type>
</pk>
<pk>
<absi>2554.960481657166</absi>
<area>706.9643195533179</area>
<chisq>17608.75911643516</chisq>
<goodn>21920.40660817865</goodn>
<goodn2>0.9570664588223270</goodn2>
<ind>184235.2525942650</ind>
<lind>184216.0000000000</lind>
<lmass>2501.014642683533</lmass>
<mass>2501.261071417990</mass>
<massemg>2501.236693728189</massemg>
<massgaussian>2501.267242730020</massgaussian>
<meth>4</meth>
<reso>28078.71316611889</reso>
<rind>184719.0000000000</rind>
<rmass>2507.456922231525</rmass>
<s2n>6.907287654623168</s2n>
<sigmaemg>0.02732861705408141</sigmaemg>
<tauemg>0.04191164530220704</tauemg>
<type>0</type>
</pk>
<pk>
<absi>794.3767831735264</absi>
<area>384.1191310750869</area>
<chisq>9143.867568860120</chisq>
<goodn>1524.178421480140</goodn>
<goodn2>0.8403665213029575</goodn2>
<ind>243145.8706582586</ind>
<lind>243123.0000000000</lind>
<lmass>3312.019055342895</lmass>
<mass>3312.356092976808</mass>
<massemg>3312.322503939462</massemg>
<massgaussian>3312.363281165012</massgaussian>
<meth>4</meth>
<reso>27055.97113022305</reso>
<rind>243571.0000000000</rind>
<rmass>3318.624223892810</rmass>
<s2n>9.290674390912532</s2n>
<sigmaemg>0.03735773518064889</sigmaemg>
<tauemg>0.05823271007557196</tauemg>
<type>0</type>
</pk>
</pklist>
